elib/__init__.py
elib/absexc.py
elib/codeerror.py
elib/deverror.py
elib/dunnoerror.py
elib/hardwareerror.py
elib/logicerror.py
elib/usererror.py
errorslib-1.3.dist-info/LICENSE
errorslib-1.3.dist-info/METADATA
errorslib-1.3.dist-info/WHEEL
errorslib-1.3.dist-info/top_level.txt
errorslib-1.3.dist-info/RECORD
