Metadata-Version: 2.1
Name: errorslib
Version: 1.3
Summary: Why would you use this?
Home-page: https://github.com/manOnWebs/errorslib
Author: wowsuchdog
Author-email: kirboistic@gmail.com
Classifier: Programming Language :: Python :: 3
Classifier: Operating System :: OS Independent
Requires-Python: >=3.6
License-File: LICENSE
